splatoon_mcp_server/__init__.py
splatoon_mcp_server/__main__.py
splatoon_mcp_server/config.py
splatoon_mcp_server/server.py
splatoon_mcp_server-0.1.4.dist-info/METADATA
splatoon_mcp_server-0.1.4.dist-info/WHEEL
splatoon_mcp_server-0.1.4.dist-info/entry_points.txt
splatoon_mcp_server-0.1.4.dist-info/RECORD
