Metadata-Version: 2.4
Name: splatoon-mcp-server
Version: 0.1.4
Summary: 查询splatoon有关的信息。主要实现形式是通过查询提前准备好的excel文件中的内容
Author-email: Duang <liduang12138@gmail.com>
License: MIT
Classifier: License :: OSI Approved :: MIT License
Classifier: Programming Language :: Python :: 3.10
Requires-Python: >=3.10
Requires-Dist: mcp>=1.2.0
Requires-Dist: pydantic>=2.8.0
